{
    "configs": [
        {
            "id": "com.dishii.soh",
            "url": "https://github.com/Waterdish/Shipwright-Android",
            "author": "Waterdish",
            "name": "Ship of Harkinian",
            "preferredApkIndex": 0,
            "additionalSettings": "{\"includePrereleases\":false,\"fallbackToOlderReleases\":true,\"filterReleaseTitlesByRegEx\":\"\",\"filterReleaseNotesByRegEx\":\"\",\"verifyLatestTag\":false,\"dontSortReleasesList\":false,\"useLatestAssetDateAsReleaseDate\":false,\"trackOnly\":false,\"versionExtractionRegEx\":\"\",\"matchGroupToUse\":\"\",\"versionDetection\":true,\"releaseDateAsVersion\":false,\"useVersionCodeAsOSVersion\":false,\"apkFilterRegEx\":\"\",\"invertAPKFilter\":false,\"autoApkFilterByArch\":true,\"appName\":\"\",\"exemptFromBackgroundUpdates\":false,\"skipUpdateNotifications\":false,\"about\":\"\"}"
        }
    ],
    "categories": [
        "games"
    ],
    "optionalOrderIndex": 28
}