{
    "configs": [
        {
            "id":"org.linphone",
            "url":"https://download.linphone.org/releases/android/",
            "author":"Belledonne Communications",
            "name":"Linphone",
            "additionalSettings":"{\"defaultPseudoVersioningMethod\":\"APKLinkHash\",\"trackOnly\":false,\"versionExtractionRegEx\":\"\\\\d+.\\\\d+.\\\\d+\",\"matchGroupToUse\":\"\",\"versionDetection\":true,\"useVersionCodeAsOSVersion\":false,\"apkFilterRegEx\":\"linphone-android-\\\\d+.\\\\d+.\\\\d+.apk\"}"
        }
    ],
    "icon": "https://gitlab.linphone.org/BC/public/linphone-android/-/raw/master/app/src/main/res/mipmap-hdpi/ic_launcher.png",
    "categories": [
        "dialer",
        "messaging"
    ],
    "description": {
        "en": "An open source app offering free audio/video calls and text messaging."
    }
}